wildlife_tools/__init__.py
wildlife_tools/tools.py
wildlife_tools/data/__init__.py
wildlife_tools/data/dataset.py
wildlife_tools/data/split.py
wildlife_tools/data/transform.py
wildlife_tools/features/__init__.py
wildlife_tools/features/base.py
wildlife_tools/features/deep.py
wildlife_tools/features/memory.py
wildlife_tools/features/sift.py
wildlife_tools/features/superpoint.py
wildlife_tools/inference/__init__.py
wildlife_tools/inference/classifier.py
wildlife_tools/similarity/__init__.py
wildlife_tools/similarity/base.py
wildlife_tools/similarity/cosine.py
wildlife_tools/similarity/descriptors.py
wildlife_tools/similarity/loftr.py
wildlife_tools/train/__init__.py
wildlife_tools/train/backbone.py
wildlife_tools/train/callbacks.py
wildlife_tools/train/objective.py
wildlife_tools/train/optim.py
wildlife_tools/train/trainer.py
wildlife_tools-0.0.9.dist-info/LICENSE
wildlife_tools-0.0.9.dist-info/METADATA
wildlife_tools-0.0.9.dist-info/WHEEL
wildlife_tools-0.0.9.dist-info/top_level.txt
wildlife_tools-0.0.9.dist-info/RECORD
