Metadata-Version: 2.1
Name: wildlife-tools
Version: 0.0.9
Summary: Tools for using wildlife re-identification datasets.
Author-email: Vojtěch Čermák <cermak.vojtech@seznam.cz>
Maintainer-email: Vojtěch Čermák <cermak.vojtech@seznam.cz>
License: MIT License
Project-URL: Homepage, https://github.com/WildlifeDatasets/wildlife-tools
Project-URL: Documentation, https://wildlifedatasets.github.io/wildlife-tools/
Project-URL: Bug Tracker, https://github.com/WildlifeDatasets/wildlife-tools/issues
Keywords: wildlife,re-identification,datasets,machine learning
Classifier: Programming Language :: Python :: 3
Classifier: License :: OSI Approved :: MIT License
Classifier: Operating System :: OS Independent
Requires-Python: >=3.8
License-File: LICENSE
Requires-Dist: torch >=2.0.1
Requires-Dist: timm >=0.9.2
Requires-Dist: numpy >=1.19.4
Requires-Dist: pandas >=1.1.4
Requires-Dist: tqdm >=4.62.3
Requires-Dist: opencv-python >=4.5.5.62
Requires-Dist: Pillow >=7.1.2
Requires-Dist: scikit-learn >=1.0.1
Requires-Dist: pycocotools
Requires-Dist: tensorboard
Requires-Dist: pytorch-metric-learning
Requires-Dist: transformers >=4.30.2
Requires-Dist: wildlife-datasets >=0.3.4
Requires-Dist: kornia >=0.6.12
Requires-Dist: faiss-gpu ; platform_system != "Windows"
Requires-Dist: faiss-cpu ; platform_system == "Windows"
